psy_transect/__init__.py
psy_transect/_version.py
psy_transect/maps.py
psy_transect/plotters.py
psy_transect/plugin.py
psy_transect/py.typed
psy_transect/utils.py
psy_transect-0.1.0.dist-info/CC-BY-4.0.txt
psy_transect-0.1.0.dist-info/CC0-1.0.txt
psy_transect-0.1.0.dist-info/LGPL-3.0-only.txt
psy_transect-0.1.0.dist-info/METADATA
psy_transect-0.1.0.dist-info/WHEEL
psy_transect-0.1.0.dist-info/entry_points.txt
psy_transect-0.1.0.dist-info/top_level.txt
psy_transect-0.1.0.dist-info/RECORD
